wdlg/__init__.py
wdlg/filedialog.py
wdlg/messagebox.py
wdlg-0.0.2.dist-info/LICENSE.txt
wdlg-0.0.2.dist-info/METADATA
wdlg-0.0.2.dist-info/WHEEL
wdlg-0.0.2.dist-info/top_level.txt
wdlg-0.0.2.dist-info/RECORD
