Metadata-Version: 2.1
Name: wdlg
Version: 0.0.2
Summary: dialog library for windows
Home-page: https://github.com/m-m-git/wdlg
License: BSD Zero Clause License
Keywords: windows,dialog,dialogs,filedialog,filedialogs
Platform: windows
Classifier: Environment :: Win32 (MS Windows)
Classifier: Intended Audience :: Developers
Classifier: License :: OSI Approved
Classifier: Operating System :: Microsoft :: Windows
Classifier: Programming Language :: Python :: 3
Classifier: Programming Language :: Python :: Implementation :: CPython
Classifier: Topic :: Software Development :: Libraries
Classifier: Topic :: Software Development :: Libraries :: Python Modules
Requires-Python: >=3.9
License-File: LICENSE.txt
